sorted_mkdn/__init__.py
sorted_mkdn/sorted_mkdn.py
sorted_mkdn/version.py
sorted_mkdn-0.1.2.data/data/LICENSE
sorted_mkdn-0.1.2.data/data/README.md
sorted_mkdn-0.1.2.dist-info/METADATA
sorted_mkdn-0.1.2.dist-info/RECORD
sorted_mkdn-0.1.2.dist-info/WHEEL
sorted_mkdn-0.1.2.dist-info/entry_points.txt
sorted_mkdn-0.1.2.dist-info/top_level.txt
