Metadata-Version: 2.1
Name: sorted-mkdn
Version: 0.1.2
Summary: Sorts markdown stars
Home-page: https://github.com/jondot/sorted-mkdn
Author: Dotan Nahum
Author-email: jondotan@gmail.com
License: Copyright (c) 2012, Kenneth Reitz
Requires-Dist: toolz
Requires-Dist: docopt
Requires-Dist: mistune
